django_iso8601/__init__.py
django_iso8601/fields.py
django_iso8601/widgets.py
django_iso8601-1.1.0.dist-info/LICENSE.txt
django_iso8601-1.1.0.dist-info/METADATA
django_iso8601-1.1.0.dist-info/RECORD
django_iso8601-1.1.0.dist-info/WHEEL
django_iso8601-1.1.0.dist-info/top_level.txt
django_iso8601-1.1.0.dist-info/zip-safe
