Metadata-Version: 2.1
Name: django-iso8601
Version: 1.1.0
Summary: Django tools for working with ISO 8601
Home-page: http://github.com/k0001/django-iso8601
Author: Renzo Carbonara
Author-email: gnuk0001@gmail.com
License: BSD
Keywords: django iso8601 dates times datetime fields validation
Platform: UNKNOWN
Classifier: Development Status :: 5 - Production/Stable
Classifier: Environment :: Web Environment
Classifier: Framework :: Django
Classifier: Intended Audience :: Developers
Classifier: License :: OSI Approved :: BSD License
Classifier: Operating System :: OS Independent
Classifier: Programming Language :: Python
Classifier: Topic :: Internet :: WWW/HTTP
Classifier: Topic :: Internet :: WWW/HTTP :: Dynamic Content
Classifier: Topic :: Software Development :: Libraries :: Application Frameworks
Classifier: Topic :: Software Development :: Libraries :: Python Modules
Classifier: Programming Language :: Python :: 2.7
Classifier: Programming Language :: Python :: 3.5
Classifier: Programming Language :: Python :: 3.6
Classifier: Programming Language :: Python :: 3.7
Requires-Dist: Django (>=1.10)
Requires-Dist: isodate (>=0.4)
